ubc_chbe_computational_methods/__init__.py
ubc_chbe_computational_methods/linear_nonlinear_systems.py
ubc_chbe_computational_methods/numerical_integration.py
ubc_chbe_computational_methods/ode_solve.py
ubc_chbe_computational_methods/regression.py
ubc_chbe_computational_methods/root_finding.py
ubc_chbe_computational_methods-0.1.3.dist-info/LICENSE
ubc_chbe_computational_methods-0.1.3.dist-info/METADATA
ubc_chbe_computational_methods-0.1.3.dist-info/WHEEL
ubc_chbe_computational_methods-0.1.3.dist-info/top_level.txt
ubc_chbe_computational_methods-0.1.3.dist-info/RECORD
