Metadata-Version: 2.1
Name: ubc-chbe-computational-methods
Version: 0.1.3
Summary: Essential python functions for numerical techniques
Home-page: https://github.com/OpenChemE/Computational_Methods
Author: Arman Seyed-Ahmadi
Author-email: arman.awn@gmail.com
License: GPLv3
Platform: UNKNOWN
Classifier: Programming Language :: Python :: 3
Requires-Dist: matplotlib
Requires-Dist: numpy
Requires-Dist: pandas
